behave4cmd0/__all_steps__.py
behave4cmd0/__init__.py
behave4cmd0/__setup.py
behave4cmd0/command_shell.py
behave4cmd0/command_shell_proc.py
behave4cmd0/command_steps.py
behave4cmd0/command_util.py
behave4cmd0/failing_steps.py
behave4cmd0/note_steps.py
behave4cmd0/passing_steps.py
behave4cmd0/pathutil.py
behave4cmd0/setup_command_shell.py
behave4cmd0/textutil.py
behave4cmd0/log/__init__.py
behave4cmd0/log/steps.py
behave_html_pretty_formatter/__init__.py
behave_html_pretty_formatter/behave.css
behave_html_pretty_formatter/behave.js
behave_html_pretty_formatter/behave.min.css
behave_html_pretty_formatter/behave.min.js
behave_html_pretty_formatter/html_pretty.py
behave_html_pretty_formatter-1.16.1.dist-info/licenses/LICENSE
behave_html_pretty_formatter-1.16.1.dist-info/METADATA
behave_html_pretty_formatter-1.16.1.dist-info/WHEEL
behave_html_pretty_formatter-1.16.1.dist-info/top_level.txt
behave_html_pretty_formatter-1.16.1.dist-info/RECORD
