Metadata-Version: 2.4
Name: behave-html-pretty-formatter
Version: 1.16.1
Summary: Pretty HTML Formatter for Behave
Author-email: Michal Odehnal <modehnal@redhat.com>, Filip Pokryvka <fpokryvk@redhat.com>, Peter Bittner <django@bittner.it>, Luca Macavero <luca.macavero@dorbit.space>
Maintainer-email: Michal Odehnal <modehnal@redhat.com>, Filip Pokryvka <fpokryvk@redhat.com>
License:                     GNU GENERAL PUBLIC LICENSE
Project-URL: homepage, https://github.com/behave-contrib/behave-html-pretty-formatter
Keywords: behave,formatter
Classifier: Development Status :: 5 - Production/Stable
Classifier: Framework :: Django
Classifier: Intended Audience :: Information Technology
Classifier: License :: OSI Approved :: GNU General Public License v3 (GPLv3)
Classifier: Operating System :: OS Independent
Classifier: Programming Language :: Python :: 3
Classifier: Programming Language :: Python :: 3.6
Classifier: Programming Language :: Python :: 3.7
Classifier: Programming Language :: Python :: 3.8
Classifier: Programming Language :: Python :: 3.9
Classifier: Programming Language :: Python :: 3.10
Classifier: Programming Language :: Python :: 3.11
Classifier: Programming Language :: Python :: Implementation :: CPython
Classifier: Programming Language :: Python :: Implementation :: PyPy
Classifier: Topic :: Software Development :: Testing
Classifier: Topic :: Software Development :: Testing :: BDD
Requires-Python: >=3.6
License-File: LICENSE
Requires-Dist: behave>=1.3.0
Requires-Dist: dominate==2.9.0
Requires-Dist: markdown
Dynamic: license-file
